Metadata-Version: 1.1
Name: django-multipleselectfield
Version: 0.2.0.post2
Summary: Django multiple select field
Home-page: https://github.com/goinnn/django-multiselectfield
Author: Pablo Martin
Author-email: goinnn@gmail.com
License: LGPL 3
Keywords: django,multiple,select,field,choices
Platform: UNKNOWN
Classifier: Development Status :: 4 - Beta
Classifier: Framework :: Django
Classifier: License :: OSI Approved :: GNU Library or Lesser General Public License (LGPL)
Classifier: Programming Language :: Python :: 2
Classifier: Programming Language :: Python :: 2.6
Classifier: Programming Language :: Python :: 2.7
Classifier: Programming Language :: Python :: 3
Classifier: Programming Language :: Python :: 3.3
Classifier: Programming Language :: Python :: 3.4
Classifier: Programming Language :: Python :: 3.5
Classifier: Programming Language :: Python :: 3.6
